{
    "/js/main.bundle.js": "/js/main.bundle.js?id=75c2bb72ec97cd2c5baa",
    "/css/main.bundle.css": "/css/main.bundle.css?id=fa9fbb03c52aeba83403",
    "/css/print.css": "/css/print.css?id=533a9a64fe5d07418d2e",
    "/js/main.bundle.js.map": "/js/main.bundle.js.map?id=990020bc6e3ca60e1d03",
    "/css/main.bundle.css.map": "/css/main.bundle.css.map?id=210b36dfe6db11c0641c",
    "/css/print.css.map": "/css/print.css.map?id=0b26739fe5896b437b10",
    "/js/print.bundle.js": "/js/print.bundle.js?id=b3b16cf2846c5acc38d2",
    "/js/print.bundle.js.map": "/js/print.bundle.js.map?id=7106d45d704bcf0918eb"
}